{
    "group": {
        "comments": [],
        "desc": "Security model for PKI",
        "groups": [
            {
                "comments": [],
                "count": 0,
                "groups": [],
                "id": "repeating",
                "points": [
                    {
                        "access": "rw",
                        "comments": [],
                        "id": "Cert",
                        "len": null,
                        "mandatory": "true",
                        "sf": null,
                        "symbols": [],
                        "type": "uint16",
                        "units": null,
                        "value": null
                    }
                ]
            }
        ],
        "id": "model_9",
        "label": "Set Operator Security Certificate",
        "points": [
            {
                "access": "r",
                "comments": [],
                "desc": "model_9 model ID.",
                "id": "ID",
                "label": "Model ID",
                "mandatory": "true",
                "symbols": [],
                "type": "uint16",
                "value": 9
            },
            {
                "access": "r",
                "comments": [],
                "desc": "model_9 model length.",
                "id": "L",
                "label": "Model Length",
                "mandatory": "true",
                "symbols": [],
                "type": "uint16"
            },
            {
                "access": "rw",
                "comments": [],
                "id": "CertUID",
                "len": null,
                "mandatory": "true",
                "sf": null,
                "symbols": [],
                "type": "uint16",
                "units": null,
                "value": null
            },
            {
                "access": "rw",
                "comments": [],
                "id": "CertRole",
                "len": null,
                "mandatory": "true",
                "sf": null,
                "symbols": [],
                "type": "uint16",
                "units": null,
                "value": null
            },
            {
                "access": "rw",
                "comments": [],
                "id": "Fmt",
                "len": null,
                "mandatory": "true",
                "sf": null,
                "symbols": [
                    {
                        "comments": [],
                        "id": "NONE",
                        "value": 0
                    },
                    {
                        "comments": [],
                        "id": "X509_PEM",
                        "value": 1
                    },
                    {
                        "comments": [],
                        "id": "X509_DER",
                        "value": 2
                    }
                ],
                "type": "enum16",
                "units": null,
                "value": null
            },
            {
                "access": "rw",
                "comments": [],
                "id": "Typ",
                "len": null,
                "mandatory": "true",
                "sf": null,
                "symbols": [
                    {
                        "comments": [],
                        "id": "DEV_KEY_PAIR",
                        "value": 0
                    },
                    {
                        "comments": [],
                        "id": "DEV_SHARED_KEY",
                        "value": 1
                    },
                    {
                        "comments": [],
                        "id": "OPERATOR_PUB",
                        "value": 2
                    },
                    {
                        "comments": [],
                        "id": "OPERATOR_SHARED",
                        "value": 3
                    },
                    {
                        "comments": [],
                        "id": "CA_PUB",
                        "value": 4
                    }
                ],
                "type": "enum16",
                "units": null,
                "value": null
            },
            {
                "access": "rw",
                "comments": [],
                "id": "TotLn",
                "len": null,
                "mandatory": "true",
                "sf": null,
                "symbols": [],
                "type": "uint16",
                "units": null,
                "value": null
            },
            {
                "access": "rw",
                "comments": [],
                "id": "FrgLn",
                "len": null,
                "mandatory": "true",
                "sf": null,
                "symbols": [],
                "type": "uint16",
                "units": null,
                "value": null
            },
            {
                "access": "rw",
                "comments": [],
                "id": "Frg1",
                "len": null,
                "mandatory": "true",
                "sf": null,
                "symbols": [],
                "type": "uint16",
                "units": null,
                "value": null
            },
            {
                "access": "rw",
                "comments": [],
                "id": "Frg2",
                "len": null,
                "mandatory": "true",
                "sf": null,
                "symbols": [],
                "type": "uint16",
                "units": null,
                "value": null
            },
            {
                "access": "rw",
                "comments": [],
                "id": "Frg3",
                "len": null,
                "mandatory": "true",
                "sf": null,
                "symbols": [],
                "type": "uint16",
                "units": null,
                "value": null
            },
            {
                "access": "rw",
                "comments": [],
                "id": "Frg4",
                "len": null,
                "mandatory": "true",
                "sf": null,
                "symbols": [],
                "type": "uint16",
                "units": null,
                "value": null
            },
            {
                "access": "rw",
                "comments": [],
                "id": "Frg5",
                "len": null,
                "mandatory": "true",
                "sf": null,
                "symbols": [],
                "type": "uint16",
                "units": null,
                "value": null
            },
            {
                "access": "rw",
                "comments": [],
                "id": "Frg6",
                "len": null,
                "mandatory": "true",
                "sf": null,
                "symbols": [],
                "type": "uint16",
                "units": null,
                "value": null
            },
            {
                "access": "rw",
                "comments": [],
                "id": "Frg7",
                "len": null,
                "mandatory": "true",
                "sf": null,
                "symbols": [],
                "type": "uint16",
                "units": null,
                "value": null
            },
            {
                "access": "rw",
                "comments": [],
                "id": "Frg8",
                "len": null,
                "mandatory": "true",
                "sf": null,
                "symbols": [],
                "type": "uint16",
                "units": null,
                "value": null
            },
            {
                "access": "rw",
                "comments": [],
                "id": "Frg9",
                "len": null,
                "mandatory": "true",
                "sf": null,
                "symbols": [],
                "type": "uint16",
                "units": null,
                "value": null
            },
            {
                "access": "rw",
                "comments": [],
                "id": "Frg10",
                "len": null,
                "mandatory": "true",
                "sf": null,
                "symbols": [],
                "type": "uint16",
                "units": null,
                "value": null
            },
            {
                "access": "rw",
                "comments": [],
                "id": "Frg11",
                "len": null,
                "mandatory": "true",
                "sf": null,
                "symbols": [],
                "type": "uint16",
                "units": null,
                "value": null
            },
            {
                "access": "rw",
                "comments": [],
                "id": "Frg12",
                "len": null,
                "mandatory": "true",
                "sf": null,
                "symbols": [],
                "type": "uint16",
                "units": null,
                "value": null
            },
            {
                "access": "rw",
                "comments": [],
                "id": "Frg13",
                "len": null,
                "mandatory": "true",
                "sf": null,
                "symbols": [],
                "type": "uint16",
                "units": null,
                "value": null
            },
            {
                "access": "rw",
                "comments": [],
                "id": "Frg14",
                "len": null,
                "mandatory": "true",
                "sf": null,
                "symbols": [],
                "type": "uint16",
                "units": null,
                "value": null
            },
            {
                "access": "rw",
                "comments": [],
                "id": "Frg15",
                "len": null,
                "mandatory": "true",
                "sf": null,
                "symbols": [],
                "type": "uint16",
                "units": null,
                "value": null
            },
            {
                "access": "rw",
                "comments": [],
                "id": "Frg16",
                "len": null,
                "mandatory": "true",
                "sf": null,
                "symbols": [],
                "type": "uint16",
                "units": null,
                "value": null
            },
            {
                "access": "rw",
                "comments": [],
                "id": "Frg17",
                "len": null,
                "mandatory": "true",
                "sf": null,
                "symbols": [],
                "type": "uint16",
                "units": null,
                "value": null
            },
            {
                "access": "rw",
                "comments": [],
                "id": "Frg18",
                "len": null,
                "mandatory": "true",
                "sf": null,
                "symbols": [],
                "type": "uint16",
                "units": null,
                "value": null
            },
            {
                "access": "rw",
                "comments": [],
                "id": "Frg19",
                "len": null,
                "mandatory": "true",
                "sf": null,
                "symbols": [],
                "type": "uint16",
                "units": null,
                "value": null
            },
            {
                "access": "rw",
                "comments": [],
                "id": "Frg20",
                "len": null,
                "mandatory": "true",
                "sf": null,
                "symbols": [],
                "type": "uint16",
                "units": null,
                "value": null
            },
            {
                "access": "rw",
                "comments": [],
                "id": "Frg21",
                "len": null,
                "mandatory": "true",
                "sf": null,
                "symbols": [],
                "type": "uint16",
                "units": null,
                "value": null
            },
            {
                "access": "rw",
                "comments": [],
                "id": "Frg22",
                "len": null,
                "mandatory": "true",
                "sf": null,
                "symbols": [],
                "type": "uint16",
                "units": null,
                "value": null
            },
            {
                "access": "rw",
                "comments": [],
                "id": "Frg23",
                "len": null,
                "mandatory": "true",
                "sf": null,
                "symbols": [],
                "type": "uint16",
                "units": null,
                "value": null
            },
            {
                "access": "rw",
                "comments": [],
                "id": "Frg24",
                "len": null,
                "mandatory": "true",
                "sf": null,
                "symbols": [],
                "type": "uint16",
                "units": null,
                "value": null
            },
            {
                "access": "rw",
                "comments": [],
                "id": "Frg25",
                "len": null,
                "mandatory": "true",
                "sf": null,
                "symbols": [],
                "type": "uint16",
                "units": null,
                "value": null
            },
            {
                "access": "rw",
                "comments": [],
                "id": "Frg26",
                "len": null,
                "mandatory": "true",
                "sf": null,
                "symbols": [],
                "type": "uint16",
                "units": null,
                "value": null
            },
            {
                "access": "rw",
                "comments": [],
                "id": "Frg27",
                "len": null,
                "mandatory": "true",
                "sf": null,
                "symbols": [],
                "type": "uint16",
                "units": null,
                "value": null
            },
            {
                "access": "rw",
                "comments": [],
                "id": "Frg28",
                "len": null,
                "mandatory": "true",
                "sf": null,
                "symbols": [],
                "type": "uint16",
                "units": null,
                "value": null
            },
            {
                "access": "rw",
                "comments": [],
                "id": "Frg29",
                "len": null,
                "mandatory": "true",
                "sf": null,
                "symbols": [],
                "type": "uint16",
                "units": null,
                "value": null
            },
            {
                "access": "rw",
                "comments": [],
                "id": "Frg30",
                "len": null,
                "mandatory": "true",
                "sf": null,
                "symbols": [],
                "type": "uint16",
                "units": null,
                "value": null
            },
            {
                "access": "rw",
                "comments": [],
                "id": "Frg31",
                "len": null,
                "mandatory": "true",
                "sf": null,
                "symbols": [],
                "type": "uint16",
                "units": null,
                "value": null
            },
            {
                "access": "rw",
                "comments": [],
                "id": "Frg32",
                "len": null,
                "mandatory": "true",
                "sf": null,
                "symbols": [],
                "type": "uint16",
                "units": null,
                "value": null
            },
            {
                "access": "rw",
                "comments": [],
                "id": "Frg33",
                "len": null,
                "mandatory": "true",
                "sf": null,
                "symbols": [],
                "type": "uint16",
                "units": null,
                "value": null
            },
            {
                "access": "rw",
                "comments": [],
                "id": "Frg34",
                "len": null,
                "mandatory": "true",
                "sf": null,
                "symbols": [],
                "type": "uint16",
                "units": null,
                "value": null
            },
            {
                "access": "rw",
                "comments": [],
                "id": "Frg35",
                "len": null,
                "mandatory": "true",
                "sf": null,
                "symbols": [],
                "type": "uint16",
                "units": null,
                "value": null
            },
            {
                "access": "rw",
                "comments": [],
                "id": "Frg36",
                "len": null,
                "mandatory": "true",
                "sf": null,
                "symbols": [],
                "type": "uint16",
                "units": null,
                "value": null
            },
            {
                "access": "rw",
                "comments": [],
                "id": "Frg37",
                "len": null,
                "mandatory": "true",
                "sf": null,
                "symbols": [],
                "type": "uint16",
                "units": null,
                "value": null
            },
            {
                "access": "rw",
                "comments": [],
                "id": "Frg38",
                "len": null,
                "mandatory": "true",
                "sf": null,
                "symbols": [],
                "type": "uint16",
                "units": null,
                "value": null
            },
            {
                "access": "rw",
                "comments": [],
                "id": "Frg39",
                "len": null,
                "mandatory": "true",
                "sf": null,
                "symbols": [],
                "type": "uint16",
                "units": null,
                "value": null
            },
            {
                "access": "rw",
                "comments": [],
                "id": "Frg40",
                "len": null,
                "mandatory": "true",
                "sf": null,
                "symbols": [],
                "type": "uint16",
                "units": null,
                "value": null
            },
            {
                "access": "rw",
                "comments": [],
                "id": "Frg41",
                "len": null,
                "mandatory": "true",
                "sf": null,
                "symbols": [],
                "type": "uint16",
                "units": null,
                "value": null
            },
            {
                "access": "rw",
                "comments": [],
                "id": "Frg42",
                "len": null,
                "mandatory": "true",
                "sf": null,
                "symbols": [],
                "type": "uint16",
                "units": null,
                "value": null
            },
            {
                "access": "rw",
                "comments": [],
                "id": "Frg43",
                "len": null,
                "mandatory": "true",
                "sf": null,
                "symbols": [],
                "type": "uint16",
                "units": null,
                "value": null
            },
            {
                "access": "rw",
                "comments": [],
                "id": "Frg44",
                "len": null,
                "mandatory": "true",
                "sf": null,
                "symbols": [],
                "type": "uint16",
                "units": null,
                "value": null
            },
            {
                "access": "rw",
                "comments": [],
                "id": "Frg45",
                "len": null,
                "mandatory": "true",
                "sf": null,
                "symbols": [],
                "type": "uint16",
                "units": null,
                "value": null
            },
            {
                "access": "rw",
                "comments": [],
                "id": "Frg46",
                "len": null,
                "mandatory": "true",
                "sf": null,
                "symbols": [],
                "type": "uint16",
                "units": null,
                "value": null
            },
            {
                "access": "rw",
                "comments": [],
                "id": "Frg47",
                "len": null,
                "mandatory": "true",
                "sf": null,
                "symbols": [],
                "type": "uint16",
                "units": null,
                "value": null
            },
            {
                "access": "rw",
                "comments": [],
                "id": "Frg48",
                "len": null,
                "mandatory": "true",
                "sf": null,
                "symbols": [],
                "type": "uint16",
                "units": null,
                "value": null
            },
            {
                "access": "rw",
                "comments": [],
                "id": "Frg49",
                "len": null,
                "mandatory": "true",
                "sf": null,
                "symbols": [],
                "type": "uint16",
                "units": null,
                "value": null
            },
            {
                "access": "rw",
                "comments": [],
                "id": "Frg50",
                "len": null,
                "mandatory": "true",
                "sf": null,
                "symbols": [],
                "type": "uint16",
                "units": null,
                "value": null
            },
            {
                "access": "rw",
                "comments": [],
                "id": "Frg51",
                "len": null,
                "mandatory": "true",
                "sf": null,
                "symbols": [],
                "type": "uint16",
                "units": null,
                "value": null
            },
            {
                "access": "rw",
                "comments": [],
                "id": "Frg52",
                "len": null,
                "mandatory": "true",
                "sf": null,
                "symbols": [],
                "type": "uint16",
                "units": null,
                "value": null
            },
            {
                "access": "rw",
                "comments": [],
                "id": "Frg53",
                "len": null,
                "mandatory": "true",
                "sf": null,
                "symbols": [],
                "type": "uint16",
                "units": null,
                "value": null
            },
            {
                "access": "rw",
                "comments": [],
                "id": "Frg54",
                "len": null,
                "mandatory": "true",
                "sf": null,
                "symbols": [],
                "type": "uint16",
                "units": null,
                "value": null
            },
            {
                "access": "rw",
                "comments": [],
                "id": "Frg55",
                "len": null,
                "mandatory": "true",
                "sf": null,
                "symbols": [],
                "type": "uint16",
                "units": null,
                "value": null
            },
            {
                "access": "rw",
                "comments": [],
                "id": "Frg56",
                "len": null,
                "mandatory": "true",
                "sf": null,
                "symbols": [],
                "type": "uint16",
                "units": null,
                "value": null
            },
            {
                "access": "rw",
                "comments": [],
                "id": "Frg57",
                "len": null,
                "mandatory": "true",
                "sf": null,
                "symbols": [],
                "type": "uint16",
                "units": null,
                "value": null
            },
            {
                "access": "rw",
                "comments": [],
                "id": "Frg58",
                "len": null,
                "mandatory": "true",
                "sf": null,
                "symbols": [],
                "type": "uint16",
                "units": null,
                "value": null
            },
            {
                "access": "rw",
                "comments": [],
                "id": "Frg59",
                "len": null,
                "mandatory": "true",
                "sf": null,
                "symbols": [],
                "type": "uint16",
                "units": null,
                "value": null
            },
            {
                "access": "rw",
                "comments": [],
                "id": "Frg60",
                "len": null,
                "mandatory": "true",
                "sf": null,
                "symbols": [],
                "type": "uint16",
                "units": null,
                "value": null
            },
            {
                "access": "rw",
                "comments": [],
                "id": "Frg61",
                "len": null,
                "mandatory": "true",
                "sf": null,
                "symbols": [],
                "type": "uint16",
                "units": null,
                "value": null
            },
            {
                "access": "rw",
                "comments": [],
                "id": "Frg62",
                "len": null,
                "mandatory": "true",
                "sf": null,
                "symbols": [],
                "type": "uint16",
                "units": null,
                "value": null
            },
            {
                "access": "rw",
                "comments": [],
                "id": "Frg63",
                "len": null,
                "mandatory": "true",
                "sf": null,
                "symbols": [],
                "type": "uint16",
                "units": null,
                "value": null
            },
            {
                "access": "rw",
                "comments": [],
                "id": "Frg64",
                "len": null,
                "mandatory": "true",
                "sf": null,
                "symbols": [],
                "type": "uint16",
                "units": null,
                "value": null
            },
            {
                "access": "rw",
                "comments": [],
                "id": "Frg65",
                "len": null,
                "mandatory": "true",
                "sf": null,
                "symbols": [],
                "type": "uint16",
                "units": null,
                "value": null
            },
            {
                "access": "rw",
                "comments": [],
                "id": "Frg66",
                "len": null,
                "mandatory": "true",
                "sf": null,
                "symbols": [],
                "type": "uint16",
                "units": null,
                "value": null
            },
            {
                "access": "rw",
                "comments": [],
                "id": "Frg67",
                "len": null,
                "mandatory": "true",
                "sf": null,
                "symbols": [],
                "type": "uint16",
                "units": null,
                "value": null
            },
            {
                "access": "rw",
                "comments": [],
                "id": "Frg68",
                "len": null,
                "mandatory": "true",
                "sf": null,
                "symbols": [],
                "type": "uint16",
                "units": null,
                "value": null
            },
            {
                "access": "rw",
                "comments": [],
                "id": "Frg69",
                "len": null,
                "mandatory": "true",
                "sf": null,
                "symbols": [],
                "type": "uint16",
                "units": null,
                "value": null
            },
            {
                "access": "rw",
                "comments": [],
                "id": "Frg70",
                "len": null,
                "mandatory": "true",
                "sf": null,
                "symbols": [],
                "type": "uint16",
                "units": null,
                "value": null
            },
            {
                "access": "rw",
                "comments": [],
                "id": "Frg71",
                "len": null,
                "mandatory": "true",
                "sf": null,
                "symbols": [],
                "type": "uint16",
                "units": null,
                "value": null
            },
            {
                "access": "rw",
                "comments": [],
                "id": "Frg72",
                "len": null,
                "mandatory": "true",
                "sf": null,
                "symbols": [],
                "type": "uint16",
                "units": null,
                "value": null
            },
            {
                "access": "rw",
                "comments": [],
                "id": "Frg73",
                "len": null,
                "mandatory": "true",
                "sf": null,
                "symbols": [],
                "type": "uint16",
                "units": null,
                "value": null
            },
            {
                "access": "rw",
                "comments": [],
                "id": "Frg74",
                "len": null,
                "mandatory": "true",
                "sf": null,
                "symbols": [],
                "type": "uint16",
                "units": null,
                "value": null
            },
            {
                "access": "rw",
                "comments": [],
                "id": "Frg75",
                "len": null,
                "mandatory": "true",
                "sf": null,
                "symbols": [],
                "type": "uint16",
                "units": null,
                "value": null
            },
            {
                "access": "rw",
                "comments": [],
                "id": "Frg78",
                "len": null,
                "mandatory": "true",
                "sf": null,
                "symbols": [],
                "type": "uint16",
                "units": null,
                "value": null
            },
            {
                "access": "rw",
                "comments": [],
                "id": "Frg79",
                "len": null,
                "mandatory": "true",
                "sf": null,
                "symbols": [],
                "type": "uint16",
                "units": null,
                "value": null
            },
            {
                "access": "rw",
                "comments": [],
                "id": "Frg80",
                "len": null,
                "mandatory": "true",
                "sf": null,
                "symbols": [],
                "type": "uint16",
                "units": null,
                "value": null
            },
            {
                "access": "rw",
                "comments": [],
                "id": "Ts",
                "len": null,
                "mandatory": "true",
                "sf": null,
                "symbols": [],
                "type": "uint32",
                "units": null,
                "value": null
            },
            {
                "access": "rw",
                "comments": [],
                "id": "Ms",
                "len": null,
                "mandatory": "true",
                "sf": null,
                "symbols": [],
                "type": "uint16",
                "units": null,
                "value": null
            },
            {
                "access": "rw",
                "comments": [],
                "id": "Seq",
                "len": null,
                "mandatory": "true",
                "sf": null,
                "symbols": [],
                "type": "uint16",
                "units": null,
                "value": null
            },
            {
                "access": "rw",
                "comments": [],
                "id": "UID",
                "len": null,
                "mandatory": "true",
                "sf": null,
                "symbols": [],
                "type": "uint16",
                "units": null,
                "value": null
            },
            {
                "access": "rw",
                "comments": [],
                "id": "Role",
                "len": null,
                "mandatory": "true",
                "sf": null,
                "symbols": [],
                "type": "uint16",
                "units": null,
                "value": null
            },
            {
                "access": "rw",
                "comments": [],
                "id": "Alg",
                "len": null,
                "mandatory": "true",
                "sf": null,
                "symbols": [
                    {
                        "comments": [],
                        "id": "NONE",
                        "value": 0
                    },
                    {
                        "comments": [],
                        "id": "AES-GMAC-64",
                        "value": 1
                    },
                    {
                        "comments": [],
                        "id": "ECC-256",
                        "value": 2
                    }
                ],
                "type": "enum16",
                "units": null,
                "value": null
            },
            {
                "access": "rw",
                "comments": [],
                "id": "N",
                "len": null,
                "mandatory": "true",
                "sf": null,
                "symbols": [],
                "type": "uint16",
                "units": null,
                "value": null
            }
        ]
    },
    "id": 9
}