<sunSpecModels v="1">

  <!-- 308: Mini Met Model -->
  <model id="308" len="4" name="mini_met">
    <block len="4" type="fixed">
      <point id="GHI" offset="0" type="uint16" len="1" units="W/m2" />
      <point id="TmpBOM" offset="1" type="int16" len="1" sf="-1" units="C" />
      <point id="TmpAmb" offset="2" type="int16" len="1" sf="-1" units="C" />
      <point id="WndSpd" offset="3" type="uint16" len="1" units="m/s" />
    </block>
  </model>
  <strings id="308" locale="en">
    <model>
      <label>Mini Met Model</label>
      <description>Include to support a few basic measurements</description>
      <notes/>
    </model>
    <point id="GHI">
      <label>GHI</label>
      <description>Global Horizontal Irradiance</description>
      <notes/>
    </point>
    <point id="TmpBOM">
      <label>Temp</label>
      <description>Back of module temperature measurement</description>
      <notes/>
    </point>
    <point id="TmpAmb">
      <label>Ambient Temperature</label>
      <description/>
      <notes/>
    </point>
    <point id="WndSpd">
      <label>Wind Speed</label>
      <description/>
      <notes/>
    </point>
  </strings>
</sunSpecModels>

